{
  "id": "example-cert",
  "mockSlug": "example-cert-readiness-check",
  "deckSlug": "example-cert-anki-deck",
  "gumroadPermalink": "example-cert-anki-deck",
  "examFactsKey": "example-cert",
  "category": "professional",
  "coverPanelKind": "building",
  "skipMockBankGeneration": false,
  "_notes": {
    "coverPanelKind": "building | hvac | safety | survey | datacenter | finance",
    "category": "professional | finance | academic | language | immigration",
    "userProvides": "certification name, exam body, official format, topic domains, disclaimers"
  }
}
