{
  "storeBaseUrl": "https://pixidstudio.gumroad.com",
  "defaultPriceCents": 1100,
  "products": {
    "hvac-epa-608-anki-deck": {
      "permalink": "hvac-epa-608-anki-deck",
      "gumroadProductId": "nWtdn9Nh0JVkg6pGO0AI3w==",
      "shortUrl": "https://pixidstudio.gumroad.com/l/hvac-epa-608-anki-deck",
      "createdAt": "2026-07-15T14:34:33.723Z",
      "apkgUploadedAt": "2026-07-15T14:40:00.000Z",
      "publishedAt": "2026-07-15T14:40:00.000Z"
    },
    "bms-building-automation-anki-deck": {
      "permalink": "bms-building-automation-anki-deck",
      "gumroadProductId": "KTUrMDSvx1pzQdMp82y8Ow==",
      "shortUrl": "https://pixidstudio.gumroad.com/l/bms-building-automation-anki-deck",
      "createdAt": "2026-07-15T14:44:54.540Z",
      "apkgUploadedAt": "2026-07-15T14:45:09.913Z",
      "publishedAt": "2026-07-15T14:45:09.913Z"
    },
    "leed-green-associate-anki-deck": {
      "permalink": "leed-green-associate-anki-deck",
      "gumroadProductId": "Usqr6injIvFpRpSSyyeEDg==",
      "shortUrl": "https://pixidstudio.gumroad.com/l/leed-green-associate-anki-deck",
      "createdAt": "2026-07-15T14:55:20.492Z",
      "apkgUploadedAt": "2026-07-15T14:55:46.912Z",
      "publishedAt": "2026-07-15T14:55:46.912Z"
    },
    "leed-ap-bd-c-anki-deck": {
      "permalink": "leed-ap-bd-c-anki-deck",
      "gumroadProductId": "5NuemmjGnTM8BlKsN3QqbQ==",
      "shortUrl": "https://pixidstudio.gumroad.com/l/leed-ap-bd-c-anki-deck",
      "createdAt": "2026-07-15T14:55:47.312Z",
      "apkgUploadedAt": "2026-07-15T14:56:04.779Z",
      "publishedAt": "2026-07-15T14:56:04.779Z"
    },
    "well-ap-anki-deck": {
      "permalink": "well-ap-anki-deck",
      "gumroadProductId": "ehuKhWYgus1tzGE1OqZPVw==",
      "shortUrl": "https://pixidstudio.gumroad.com/l/well-ap-anki-deck",
      "createdAt": "2026-07-15T14:56:05.216Z",
      "apkgUploadedAt": "2026-07-15T14:56:22.982Z",
      "publishedAt": "2026-07-15T14:56:22.982Z"
    },
    "cem-anki-deck": {
      "permalink": "cem-anki-deck",
      "gumroadProductId": "qdw5aGDgKXzz406stmTGYQ==",
      "shortUrl": "https://pixidstudio.gumroad.com/l/cem-anki-deck",
      "createdAt": "2026-07-15T14:56:23.379Z",
      "apkgUploadedAt": "2026-07-15T14:56:40.249Z",
      "publishedAt": "2026-07-15T14:56:40.249Z"
    },
    "ashrae-certifications-anki-deck": {
      "permalink": "ashrae-certifications-anki-deck",
      "gumroadProductId": "fO1lzOyW-oVkdYbDmy-izg==",
      "shortUrl": "https://pixidstudio.gumroad.com/l/ashrae-certifications-anki-deck",
      "createdAt": "2026-07-15T14:56:40.934Z",
      "apkgUploadedAt": "2026-07-15T14:56:58.597Z",
      "publishedAt": "2026-07-15T14:56:58.597Z"
    },
    "cdcp-anki-deck": {
      "permalink": "cdcp-anki-deck",
      "gumroadProductId": "m7iZ2hA4F22C17NtBJIRGA==",
      "shortUrl": "https://pixidstudio.gumroad.com/l/cdcp-anki-deck",
      "createdAt": "2026-07-15T14:56:59.028Z",
      "apkgUploadedAt": "2026-07-15T14:57:19.730Z",
      "publishedAt": "2026-07-15T14:57:19.730Z"
    },
    "nebosh-anki-deck": {
      "permalink": "nebosh-anki-deck",
      "gumroadProductId": "huq1oZint7Tjh860e8Fj-A==",
      "shortUrl": "https://pixidstudio.gumroad.com/l/nebosh-anki-deck",
      "createdAt": "2026-07-15T14:57:20.150Z",
      "apkgUploadedAt": "2026-07-15T14:57:38.085Z",
      "publishedAt": "2026-07-15T14:57:38.085Z"
    },
    "cfps-anki-deck": {
      "permalink": "cfps-anki-deck",
      "gumroadProductId": "tgbQOhANVlRzUqFvEpv-OA==",
      "shortUrl": "https://pixidstudio.gumroad.com/l/cfps-anki-deck",
      "createdAt": "2026-07-15T14:57:38.468Z",
      "apkgUploadedAt": "2026-07-15T14:57:55.654Z",
      "publishedAt": "2026-07-15T14:57:55.654Z"
    },
    "mrics-anki-deck": {
      "permalink": "mrics-anki-deck",
      "gumroadProductId": "rNzxIR62NW-S7iveIwBnjQ==",
      "shortUrl": "https://pixidstudio.gumroad.com/l/mrics-anki-deck",
      "createdAt": "2026-07-15T14:57:56.070Z",
      "apkgUploadedAt": "2026-07-15T14:58:13.484Z",
      "publishedAt": "2026-07-15T14:58:13.484Z"
    },
    "mrics-quantity-surveying-anki-deck": {
      "permalink": "mrics-quantity-surveying-anki-deck",
      "gumroadProductId": "VIH09RCCNXPw-26smDXnYg==",
      "shortUrl": "https://pixidstudio.gumroad.com/l/mrics-quantity-surveying-anki-deck",
      "createdAt": "2026-07-15T14:58:14.012Z",
      "apkgUploadedAt": "2026-07-15T14:58:32.631Z",
      "publishedAt": "2026-07-15T14:58:32.631Z"
    },
    "gmat-focus-anki-deck": {
      "permalink": "gmat-focus-anki-deck",
      "gumroadProductId": "I3RzQSJdnJvYXbw_OnccmA==",
      "shortUrl": "https://pixidstudio.gumroad.com/l/gmat-focus-anki-deck",
      "createdAt": "2026-07-15T14:58:33.093Z",
      "apkgUploadedAt": "2026-07-15T16:43:44.382Z",
      "publishedAt": "2026-07-15T14:58:46.504Z"
    },
    "sat-anki-deck": {
      "permalink": "sat-anki-deck",
      "gumroadProductId": "o-Oj9M6Xd_40ZcmMkAY2Kw==",
      "shortUrl": "https://pixidstudio.gumroad.com/l/sat-anki-deck",
      "createdAt": "2026-07-16T12:35:44.194Z",
      "apkgUploadedAt": "2026-07-16T13:00:05.021Z",
      "publishedAt": "2026-07-16T12:35:57.881Z"
    },
    "pmp-anki-deck": {
      "permalink": "pmp-anki-deck",
      "gumroadProductId": "QFWSwOTQ6k1mFOuNKfjt2g==",
      "shortUrl": "https://pixidstudio.gumroad.com/l/pmp-anki-deck",
      "createdAt": "2026-07-16T14:52:47.036Z",
      "apkgUploadedAt": "2026-07-16T14:53:08.448Z",
      "publishedAt": "2026-07-16T14:53:08.448Z"
    },
    "gre-anki-deck": {
      "permalink": "gre-anki-deck",
      "gumroadProductId": "KwOYuqVOy4Dp3nAonG9_-Q==",
      "shortUrl": "https://pixidstudio.gumroad.com/l/gre-anki-deck",
      "createdAt": "2026-07-16T16:09:41.369Z",
      "apkgUploadedAt": "2026-07-16T16:09:53.567Z",
      "publishedAt": "2026-07-16T16:09:53.567Z"
    },
    "leed-ap-om-anki-deck": {
      "permalink": "leed-ap-om-anki-deck",
      "gumroadProductId": "rqlmSgtYvDZFEkVVYHpI1Q==",
      "shortUrl": "https://pixidstudio.gumroad.com/l/leed-ap-om-anki-deck",
      "createdAt": "2026-07-16T16:07:51.079Z",
      "apkgUploadedAt": "2026-07-16T16:08:05.894Z",
      "publishedAt": "2026-07-16T16:08:05.894Z"
    }
  }
}
